setup.py
evinweather/__init__.py
evinweather/evinweather.py
evinweather.egg-info/PKG-INFO
evinweather.egg-info/SOURCES.txt
evinweather.egg-info/dependency_links.txt
evinweather.egg-info/requires.txt
evinweather.egg-info/top_level.txt