Metadata-Version: 2.1
Name: evinweather
Version: 1.0.0
Summary: Weather forecast data
Home-page: https://github.com/evinai
Author: Togay Tunca
Author-email: ttunca@evin-ai.com
License: MIT
Keywords: weather,forecast,openweather
Classifier: Development Status :: 3 - Alpha
Classifier: Intended Audience :: Developers
Classifier: Topic :: Software Development :: Build Tools
Classifier: License :: OSI Approved :: MIT License
